d4rk/__init__.py
d4rk/icon.py
d4rk/popup.py
d4rk/theme.py
d4rk-1.24.1.dist-info/LICENSE
d4rk-1.24.1.dist-info/METADATA
d4rk-1.24.1.dist-info/WHEEL
d4rk-1.24.1.dist-info/top_level.txt
d4rk-1.24.1.dist-info/RECORD
