Metadata-Version: 2.1
Name: d4rk
Version: 1.24.1
Summary: A Python framework with dark mode and custom icons.
Author: Hussain Luai
Author-email: hxolotl15@gmail.com
Classifier: Programming Language :: Python :: 3
Classifier: License :: OSI Approved :: MIT License
Classifier: Operating System :: OS Independent
License-File: LICENSE
